simuwater/__init__.py
simuwater/objects.py
simuwater/output.py
simuwater/simulation.py
simuwater/simuwater.py
simuwater/swmmobjects.py
simuwater/lib/__init__.py
simuwater/lib/x64/__init__.py
simuwater/lib/x64/simuwater.dll
simuwater/lib/x64/simuwater_output.dll
simuwater/lib/x64/sqlite3.dll
simuwater/lib/x64/swmm5ex.dll
simuwater/lib/x86/__init__.py
simuwater/lib/x86/simuwater.dll
simuwater/lib/x86/simuwater_output.dll
simuwater/lib/x86/sqlite3.dll
simuwater/lib/x86/swmm5ex.dll
simuwater-0.0.9.dist-info/LICENSE
simuwater-0.0.9.dist-info/METADATA
simuwater-0.0.9.dist-info/WHEEL
simuwater-0.0.9.dist-info/top_level.txt
simuwater-0.0.9.dist-info/RECORD
