Metadata-Version: 2.1
Name: simuwater
Version: 0.0.9
Summary: Simuwater is a control-oriented modelling software.
Home-page: UNKNOWN
Author: Lei Zhang
Author-email: gemini.zhang@qq.com
License: MIT
Platform: UNKNOWN
License-File: LICENSE
